type_less/__init__.py
type_less/inference.py
type_less/inject.py
type_less/replace.py
type_less-0.1.27.dist-info/METADATA
type_less-0.1.27.dist-info/WHEEL
type_less-0.1.27.dist-info/RECORD
