Metadata-Version: 2.4
Name: type-less
Version: 0.1.27
Summary: Type less types with inferred return types
Requires-Python: >=3.11
